dsnd_probability_necs_1/Binomialdistribution.py
dsnd_probability_necs_1/Gaussiandistribution.py
dsnd_probability_necs_1/Generaldistribution.py
dsnd_probability_necs_1/__init__.py
dsnd_probability_necs_1-1.2.dist-info/METADATA
dsnd_probability_necs_1-1.2.dist-info/WHEEL
dsnd_probability_necs_1-1.2.dist-info/top_level.txt
dsnd_probability_necs_1-1.2.dist-info/RECORD
