Metadata-Version: 2.4
Name: dsnd_probability_necs_1
Version: 1.2
Summary: Gaussian and Binomial distributions
Author: Necs Mobolaji
Author-email: goognecs@gmail.com
Dynamic: author
Dynamic: author-email
Dynamic: summary
